agents/SOP.py
agents/State.py
agents/__init__.py
agents/evolve.py
agents/template.py
agents/utils.py
agents/Action/__init__.py
agents/Action/base_action.py
agents/Agent/Agent.py
agents/Agent/__init__.py
agents/Component/ExtraComponent.py
agents/Component/PromptComponent.py
agents/Component/ToolComponent.py
agents/Component/__init__.py
agents/Environment/__init__.py
agents/Environment/base_environment.py
agents/LLM/__init__.py
agents/LLM/base_LLM.py
agents/Memory/__init__.py
agents/Memory/base_Memory.py
agents/Prompt/__init__.py
agents/Prompt/base_Prompts.py
mikedeanproject-0.0.1.dist-info/LICENSE
mikedeanproject-0.0.1.dist-info/METADATA
mikedeanproject-0.0.1.dist-info/WHEEL
mikedeanproject-0.0.1.dist-info/top_level.txt
mikedeanproject-0.0.1.dist-info/RECORD
