Metadata-Version: 2.1
Name: mikedeanproject
Version: 0.0.1
Summary: An Open-source Framework for Autonomous Language Agents
Home-page: https://github.com/aiwaves-cn/agents
Author: AIWaves
Author-email: contact@aiwaves.cn
License: Apache License 2.0
Classifier: Programming Language :: Python :: 3
Classifier: License :: OSI Approved :: Apache Software License
Classifier: Operating System :: OS Independent
Requires-Python: >=3.6
License-File: LICENSE
Requires-Dist: beautifulsoup4
Requires-Dist: fastapi
Requires-Dist: google-api-python-client
Requires-Dist: google-auth-oauthlib
Requires-Dist: gradio ==3.39.0
Requires-Dist: langchain
Requires-Dist: numpy
Requires-Dist: openai
Requires-Dist: pandas
Requires-Dist: Pillow
Requires-Dist: protobuf
Requires-Dist: psutil
Requires-Dist: PyYAML
Requires-Dist: Requests
Requires-Dist: selenium
Requires-Dist: sentence-transformers
Requires-Dist: setuptools
Requires-Dist: text2vec
Requires-Dist: torch
Requires-Dist: tqdm
Requires-Dist: uvicorn
